{"Error":[{"date":"2022-03-15 9:43:55","code":"ER_BAD_NULL_ERROR","errno":1048,"sqlMessage":"Column 'nama_customer' cannot be null","sqlState":"23000","sql":"INSERT INTO customer \n                            (customer_id,\nnama_customer) \n                            VALUES \n                            (NULL,\nNULL)"},{"date":"2022-03-15 9:47:45","code":"ER_BAD_NULL_ERROR","errno":1048,"sqlMessage":"Column 'nama_kandang' cannot be null","sqlState":"23000","sql":"INSERT INTO kandang \n                            (kandang_id,\nnama_kandang) \n                            VALUES \n                            ('3',\nNULL)"},{"date":"2022-03-15 9:48:17","code":"ER_DUP_ENTRY","errno":1062,"sqlMessage":"Duplicate entry '3' for key 'PRIMARY'","sqlState":"23000","sql":"INSERT INTO kandang \n                            (kandang_id,\nnama_kandang) \n                            VALUES \n                            ('3',\n'BTG')"},{"date":"2022-03-15 9:53:51","code":"ER_BAD_NULL_ERROR","errno":1048,"sqlMessage":"Column 'user_id' cannot be null","sqlState":"23000","sql":"INSERT INTO m_user \n                            (user_id,\nuser_fullname,\nrole_id,\nuser_password,\nuser_status) \n                            VALUES \n                            (NULL,\nNULL,\nNULL,\nNULL,\nNULL)"},{"date":"2022-03-15 9:54:5","code":"ER_BAD_NULL_ERROR","errno":1048,"sqlMessage":"Column 'user_fullname' cannot be null","sqlState":"23000","sql":"INSERT INTO m_user \n                            (user_id,\nuser_fullname,\nrole_id,\nuser_password,\nuser_status) \n                            VALUES \n                            ('52',\nNULL,\nNULL,\nNULL,\nNULL)"},{"date":"2022-03-15 9:55:43","code":"ER_TRUNCATED_WRONG_VALUE_FOR_FIELD","errno":1366,"sqlMessage":"Incorrect integer value: 'Bambang si bangbang' for column 'role_id' at row 1","sqlState":"HY000","sql":"INSERT INTO m_user \n                            (user_id,\nuser_fullname,\nrole_id,\nuser_password,\nuser_status) \n                            VALUES \n                            ('bambang@ymail.com',\n'Bambang si bangbang',\n'Bambang si bangbang',\n'Bambang si bangbang',\n'Bambang si bangbang')"},{"date":"2022-03-15 9:56:9","code":"ER_TRUNCATED_WRONG_VALUE_FOR_FIELD","errno":1366,"sqlMessage":"Incorrect integer value: 'Bambang si bangbang' for column 'role_id' at row 1","sqlState":"HY000","sql":"INSERT INTO m_user \n                            (user_id,\nuser_fullname,\nrole_id,\nuser_password,\nuser_status) \n                            VALUES \n                            ('bambang@ymail.com',\n'Bambang si bangbang',\n'Bambang si bangbang',\n'Bambang si bangbang',\n'Bambang si bangbang')"},{"date":"2022-03-15 9:56:18","code":"ER_BAD_NULL_ERROR","errno":1048,"sqlMessage":"Column 'user_fullname' cannot be null","sqlState":"23000","sql":"INSERT INTO m_user \n                            (user_id,\nuser_fullname,\nrole_id,\nuser_password,\nuser_status) \n                            VALUES \n                            ('bambang@ymail.com',\nNULL,\nNULL,\nNULL,\nNULL)"},{"date":"2022-03-15 9:56:24","code":"ER_TRUNCATED_WRONG_VALUE_FOR_FIELD","errno":1366,"sqlMessage":"Incorrect integer value: 'Bambang si bangbang' for column 'role_id' at row 1","sqlState":"HY000","sql":"INSERT INTO m_user \n                            (user_id,\nuser_fullname,\nrole_id,\nuser_password,\nuser_status) \n                            VALUES \n                            ('bambang@ymail.com',\n'Bambang si bangbang',\n'Bambang si bangbang',\n'Bambang si bangbang',\n'Bambang si bangbang')"},{"date":"2022-03-15 9:57:26","code":"ER_TRUNCATED_WRONG_VALUE_FOR_FIELD","errno":1366,"sqlMessage":"Incorrect integer value: 'yaya' for column 'role_id' at row 1","sqlState":"HY000","sql":"INSERT INTO m_user \n                            (user_id,\nuser_fullname,\nrole_id,\nuser_password,\nuser_status) \n                            VALUES \n                            ('yayaya@gmail.com',\n'yaya',\n'yaya',\n'yaya',\n'yaya')"},{"date":"2022-03-15 9:57:48","code":"ER_TRUNCATED_WRONG_VALUE_FOR_FIELD","errno":1366,"sqlMessage":"Incorrect integer value: 'yaya' for column 'role_id' at row 1","sqlState":"HY000","sql":"INSERT INTO m_user \n                            (user_id,\nuser_fullname,\nrole_id,\nuser_password,\nuser_status) \n                            VALUES \n                            ('yayaya@gmail.com',\n'yaya',\n'yaya',\n'yaya',\n'yaya')"},{"date":"2022-03-15 9:57:55","code":"ER_BAD_NULL_ERROR","errno":1048,"sqlMessage":"Column 'user_id' cannot be null","sqlState":"23000","sql":"INSERT INTO m_user \n                            (user_id,\nuser_fullname,\nrole_id,\nuser_password,\nuser_status) \n                            VALUES \n                            (NULL,\n'yaya',\n'yaya',\n'yaya',\n'yaya')"},{"date":"2022-03-15 9:57:59","code":"ER_BAD_NULL_ERROR","errno":1048,"sqlMessage":"Column 'user_fullname' cannot be null","sqlState":"23000","sql":"INSERT INTO m_user \n                            (user_id,\nuser_fullname,\nrole_id,\nuser_password,\nuser_status) \n                            VALUES \n                            ('yayaya@gmail.com',\nNULL,\nNULL,\nNULL,\nNULL)"},{"date":"2022-03-15 9:58:6","code":"ER_TRUNCATED_WRONG_VALUE_FOR_FIELD","errno":1366,"sqlMessage":"Incorrect integer value: 'yaya' for column 'role_id' at row 1","sqlState":"HY000","sql":"INSERT INTO m_user \n                            (user_id,\nuser_fullname,\nrole_id,\nuser_password,\nuser_status) \n                            VALUES \n                            ('yayaya@gmail.com',\n'yaya',\n'yaya',\n'yaya',\n'yaya')"},{"date":"2022-03-15 9:58:24","code":"ER_TRUNCATED_WRONG_VALUE_FOR_FIELD","errno":1366,"sqlMessage":"Incorrect integer value: 'yaya' for column 'role_id' at row 1","sqlState":"HY000","sql":"INSERT INTO m_user \n                            (user_id,\nuser_fullname,\nrole_id,\nuser_password,\nuser_status) \n                            VALUES \n                            ('yayaya@gmail.com',\n'yaya',\n'yaya',\n'yaya',\n'yaya')"},{"date":"2022-03-15 9:58:41","code":"ER_TRUNCATED_WRONG_VALUE_FOR_FIELD","errno":1366,"sqlMessage":"Incorrect integer value: 'yaya' for column 'role_id' at row 1","sqlState":"HY000","sql":"INSERT INTO m_user \n                            (user_id,\nuser_fullname,\nrole_id,\nuser_password,\nuser_status) \n                            VALUES \n                            ('yayaya@gmail.com',\n'yaya',\n'yaya',\n'yaya',\n'yaya')"},{"date":"2022-03-15 9:59:14","code":"ER_TRUNCATED_WRONG_VALUE_FOR_FIELD","errno":1366,"sqlMessage":"Incorrect integer value: 'yaya' for column 'role_id' at row 1","sqlState":"HY000","sql":"INSERT INTO m_user \n                            (user_id,\nuser_fullname,\nrole_id,\nuser_password,\nuser_status) \n                            VALUES \n                            ('yayaya@gmail.com',\n'yaya',\n'yaya',\n'yaya',\n'yaya')"},{"date":"2022-03-15 9:59:33","code":"ER_TRUNCATED_WRONG_VALUE_FOR_FIELD","errno":1366,"sqlMessage":"Incorrect integer value: 'yaya' for column 'role_id' at row 1","sqlState":"HY000","sql":"INSERT INTO m_user \n                            (user_id,\nuser_fullname,\nrole_id,\nuser_password,\nuser_status) \n                            VALUES \n                            ('yayaya@gmail.com',\n'yaya',\n'yaya',\n'yaya',\n'yaya')"},{"date":"2022-03-15 9:59:36","code":"ER_BAD_NULL_ERROR","errno":1048,"sqlMessage":"Column 'user_fullname' cannot be null","sqlState":"23000","sql":"INSERT INTO m_user \n                            (user_id,\nuser_fullname,\nrole_id,\nuser_password,\nuser_status) \n                            VALUES \n                            ('yayaya@gmail.com',\nNULL,\nNULL,\nNULL,\nNULL)"},{"date":"2022-03-15 9:59:41","code":"ER_TRUNCATED_WRONG_VALUE_FOR_FIELD","errno":1366,"sqlMessage":"Incorrect integer value: 'yaya' for column 'role_id' at row 1","sqlState":"HY000","sql":"INSERT INTO m_user \n                            (user_id,\nuser_fullname,\nrole_id,\nuser_password,\nuser_status) \n                            VALUES \n                            ('yayaya@gmail.com',\n'yaya',\n'yaya',\n'yaya',\n'yaya')"},{"date":"2022-03-15 10:0:55","code":"ER_TRUNCATED_WRONG_VALUE_FOR_FIELD","errno":1366,"sqlMessage":"Incorrect integer value: 'yaya' for column 'role_id' at row 1","sqlState":"HY000","sql":"INSERT INTO m_user \n                            (user_id,\nuser_fullname,\nrole_id,\nuser_password,\nuser_status) \n                            VALUES \n                            ('yayaya@gmail.com',\n'yaya',\n'yaya',\n'yaya',\n'yaya')"},{"date":"2022-03-15 10:1:19","code":"ER_TRUNCATED_WRONG_VALUE_FOR_FIELD","errno":1366,"sqlMessage":"Incorrect integer value: 'yaya' for column 'role_id' at row 1","sqlState":"HY000","sql":"INSERT INTO m_user \n                            (user_id,\nuser_fullname,\nrole_id,\nuser_password,\nuser_status) \n                            VALUES \n                            ('yayaya@gmail.com',\n'yaya',\n'yaya',\n'yaya',\n'yaya')"},{"date":"2022-03-15 11:5:36","code":"ER_NO_REFERENCED_ROW_2","errno":1452,"sqlMessage":"Cannot add or update a child row: a foreign key constraint fails (`pasl`.`m_role_privilage`, CONSTRAINT `fk_m_role_privilage_m_role` FOREIGN KEY (`role_id`) REFERENCES `m_role` (`role_id`) ON DELETE NO ACTION ON UPDATE NO ACTION)","sqlState":"23000","sql":"INSERT INTO m_role_privilage \n                            (role_id,\nprivilage_id,\nmodule_id) \n                            VALUES \n                            ('3',\n'2',\n'lagi test aja')"},{"date":"2022-03-15 14:11:33","code":"ER_BAD_NULL_ERROR","errno":1048,"sqlMessage":"Column 'user_fullname' cannot be null","sqlState":"23000","sql":"INSERT INTO m_user \n                            (user_id,\nuser_fullname,\nrole_id,\nuser_password,\nuser_status) \n                            VALUES \n                            ('cobalagi@yahoo.com',\nNULL,\nNULL,\nNULL,\nNULL)"},{"date":"2022-03-15 14:11:57","code":"ER_TRUNCATED_WRONG_VALUE_FOR_FIELD","errno":1366,"sqlMessage":"Incorrect integer value: 'cobain' for column 'role_id' at row 1","sqlState":"HY000","sql":"INSERT INTO m_user \n                            (user_id,\nuser_fullname,\nrole_id,\nuser_password,\nuser_status) \n                            VALUES \n                            ('cobalagi@yahoo.com',\n'cobain',\n'cobain',\n'cobain',\n'cobain')"},{"date":"2022-03-15 14:34:28","code":"ER_PARSE_ERROR","errno":1064,"sqlMessage":"You have an error in your SQL syntax; check the manual that corresponds to your MySQL server version for the right syntax to use near '= '[object Object]',\nuser_fullname = '[object Object]',\nrole_id = '[object Objec' at line 1","sqlState":"42000","sql":"UPDATE m_userSET user_id = '[object Object]',\nuser_fullname = '[object Object]',\nrole_id = '[object Object]',\nuser_password = '[object Object]',\nuser_status = '[object Object]'                                           \n                    WHERE 1=1  AND user_id = 'bambang@ymail.com'"},{"date":"2022-03-15 14:37:59","code":"ER_NO_REFERENCED_ROW_2","errno":1452,"sqlMessage":"Cannot add or update a child row: a foreign key constraint fails (`pasl`.`m_user`, CONSTRAINT `fk_m_user_m_role` FOREIGN KEY (`role_id`) REFERENCES `m_role` (`role_id`) ON DELETE NO ACTION ON UPDATE NO ACTION)","sqlState":"23000","sql":"INSERT INTO m_user \n                            (user_id,\nuser_fullname,\nrole_id,\nuser_password,\nuser_status) \n                            VALUES \n                            ('percobaan3@gmail.com',\n'gataudah',\n'4',\n'992',\n'0')"},{"date":"2022-03-15 14:46:24","code":"ER_BAD_NULL_ERROR","errno":1048,"sqlMessage":"Column 'nama_customer' cannot be null","sqlState":"23000","sql":"UPDATE customer SET customer_id = '2',\nnama_customer = NULL                                           \n                    WHERE 1=1  AND customer_id = '2'"},{"date":"2022-03-15 14:50:49","code":"ER_BAD_NULL_ERROR","errno":1048,"sqlMessage":"Column 'customer_id' cannot be null","sqlState":"23000","sql":"UPDATE customer SET customer_id = NULL,\nnama_customer = NULL                                           \n                    WHERE 1=1 "},{"date":"2022-03-15 14:50:52","code":"ER_BAD_NULL_ERROR","errno":1048,"sqlMessage":"Column 'nama_customer' cannot be null","sqlState":"23000","sql":"UPDATE customer SET customer_id = '1',\nnama_customer = NULL                                           \n                    WHERE 1=1  AND customer_id = '1'"},{"date":"2022-03-15 15:42:24","code":"ER_NO_DEFAULT_FOR_FIELD","errno":1364,"sqlMessage":"Field 'harga_ayam_jantan' doesn't have a default value","sqlState":"HY000","sql":"INSERT INTO do_masuk \n                            (no_do,\npaid_id,\nkandang_id,\nsupplier,\njumlah_ayam_jantan,\njumlah_ayam_betina,\nayam_mati) \n                            VALUES \n                            ('52',\n'YP',\n'3',\n'ALEK4',\n'40',\n'50',\n'3')"},{"date":"2022-03-15 15:42:43","code":"ER_NO_DEFAULT_FOR_FIELD","errno":1364,"sqlMessage":"Field 'harga_ayam_jantan' doesn't have a default value","sqlState":"HY000","sql":"INSERT INTO do_masuk \n                            (no_do,\npaid_id,\nkandang_id,\nsupplier,\njumlah_ayam_jantan,\njumlah_ayam_betina,\nayam_mati) \n                            VALUES \n                            ('52',\n'YP',\n'3',\n'ALEK4',\n'40',\n'50',\n'3')"},{"date":"2022-03-15 15:45:51","code":"ER_NO_DEFAULT_FOR_FIELD","errno":1364,"sqlMessage":"Field 'harga_ayam_jantan' doesn't have a default value","sqlState":"HY000","sql":"INSERT INTO do_masuk \n                            (no_do,\npaid_id,\nkandang_id,\nsupplier,\njumlah_ayam_jantan,\njumlah_ayam_betina,\nayam_mati) \n                            VALUES \n                            ('52',\n'YP',\n'3',\n'ALEK4',\n'40',\n'50',\n'3')"},{"date":"2022-03-15 16:52:14","code":"ER_NO_DEFAULT_FOR_FIELD","errno":1364,"sqlMessage":"Field 'harga_ayam_jantan' doesn't have a default value","sqlState":"HY000","sql":"INSERT INTO do_masuk \n                            (no_do,\npaid_id,\nkandang_id,\nsupplier,\njumlah_ayam_jantan,\njumlah_ayam_betina,\nayam_mati) \n                            VALUES \n                            ('52',\n'YP',\n'3',\n'ALEK4',\n'40',\n'50',\n'3')"}]}