{"Error":[{"date":"2022-09-22 11:29:11","code":"POOL_CLOSED"},{"date":"2022-09-22 11:34:0","code":"POOL_CLOSED"},{"date":"2022-09-22 11:37:12","code":"POOL_CLOSED"},{"date":"2022-09-22 11:47:42","code":"POOL_CLOSED"},{"date":"2022-09-22 11:47:42","code":"POOL_CLOSED"},{"date":"2022-09-22 13:17:37","code":"POOL_CLOSED"},{"date":"2022-09-22 13:31:3","code":"POOL_CLOSED"},{"date":"2022-09-22 13:31:12","code":"POOL_CLOSED"},{"date":"2022-09-22 13:31:13","code":"POOL_CLOSED"},{"date":"2022-09-22 13:31:36","code":"POOL_CLOSED"},{"date":"2022-09-22 13:34:37","code":"POOL_CLOSED"},{"date":"2022-09-22 13:35:59","code":"POOL_CLOSED"},{"date":"2022-09-22 13:40:2","code":"POOL_CLOSED"},{"date":"2022-09-22 13:42:16","code":"POOL_CLOSED"},{"date":"2022-09-22 13:45:4","code":"POOL_CLOSED"},{"date":"2022-09-22 13:48:9","code":"POOL_CLOSED"},{"date":"2022-09-22 13:48:45","code":"POOL_CLOSED"},{"date":"2022-09-22 13:53:52","code":"POOL_CLOSED"},{"date":"2022-09-22 14:6:37","code":"POOL_CLOSED"},{"date":"2022-09-22 14:6:47","code":"POOL_CLOSED"},{"date":"2022-09-22 14:15:56","code":"POOL_CLOSED"},{"date":"2022-09-22 14:17:7","code":"POOL_CLOSED"},{"date":"2022-09-22 14:17:7","code":"POOL_CLOSED"},{"date":"2022-09-22 14:17:21","code":"POOL_CLOSED"},{"date":"2022-09-22 14:17:33","code":"POOL_CLOSED"},{"date":"2022-09-22 14:18:53","code":"POOL_CLOSED"},{"date":"2022-09-22 14:22:22","code":"POOL_CLOSED"},{"date":"2022-09-22 14:23:2","code":"POOL_CLOSED"},{"date":"2022-09-22 14:52:40","code":"POOL_CLOSED"},{"date":"2022-09-22 14:54:12","code":"POOL_CLOSED"},{"date":"2022-09-22 14:54:14","code":"POOL_CLOSED"},{"date":"2022-09-22 14:54:21","code":"POOL_CLOSED"},{"date":"2022-09-22 15:52:15","code":"POOL_CLOSED"},{"date":"2022-09-22 16:38:34","code":"POOL_CLOSED"}]}