{"Error":[{"date":"2022-09-21 9:41:16","code":"POOL_CLOSED"},{"date":"2022-09-21 9:41:33","code":"POOL_CLOSED"},{"date":"2022-09-21 10:46:4","code":"POOL_CLOSED"},{"date":"2022-09-21 11:1:1","code":"POOL_CLOSED"},{"date":"2022-09-21 11:7:16","code":"POOL_CLOSED"},{"date":"2022-09-21 11:8:2","code":"POOL_CLOSED"},{"date":"2022-09-21 11:8:9","code":"POOL_CLOSED"},{"date":"2022-09-21 11:8:22","code":"POOL_CLOSED"},{"date":"2022-09-21 13:19:25","code":"POOL_CLOSED"},{"date":"2022-09-21 13:41:44","code":"POOL_CLOSED"},{"date":"2022-09-21 13:42:48","code":"POOL_CLOSED"},{"date":"2022-09-21 13:43:10","code":"POOL_CLOSED"},{"date":"2022-09-21 14:15:54","code":"POOL_CLOSED"},{"date":"2022-09-21 14:39:30","code":"POOL_CLOSED"},{"date":"2022-09-21 16:21:9","code":"POOL_CLOSED"},{"date":"2022-09-21 16:32:24","code":"POOL_CLOSED"}]}